setup.py
open_elections/__init__.py
open_elections.egg-info/PKG-INFO
open_elections.egg-info/SOURCES.txt
open_elections.egg-info/dependency_links.txt
open_elections.egg-info/entry_points.txt
open_elections.egg-info/requires.txt
open_elections.egg-info/top_level.txt
open_elections/dolt/__init__.py
open_elections/dolt/load_shared_voting_data.py
open_elections/dolt/tools.py
open_elections/dolt/states/__init__.py
open_elections/dolt/states/az.py
open_elections/dolt/states/ca.py
open_elections/dolt/states/co.py
open_elections/dolt/states/ct.py
open_elections/dolt/states/de.py
open_elections/dolt/states/hi.py
open_elections/dolt/states/ia.py
open_elections/dolt/states/id.py
open_elections/dolt/states/il.py
open_elections/dolt/states/in.py
open_elections/dolt/states/ks.py
open_elections/dolt/states/mo.py
open_elections/dolt/states/ms.py
open_elections/dolt/states/nh.py
open_elections/dolt/states/nj.py
open_elections/dolt/states/ny.py
open_elections/dolt/states/ok.py
open_elections/dolt/states/or.py
open_elections/dolt/states/pa.py
open_elections/dolt/states/sd.py
open_elections/dolt/states/tx.py
open_elections/dolt/states/ut.py
open_elections/dolt/states/wa.py
open_elections/dolt/states/wi.py
open_elections/dolt/states/wv.py
open_elections/tools/__init__.py
open_elections/tools/config.py
open_elections/tools/logging_helper.py
open_elections/tools/reading.py
open_elections/tools/tests/__init__.py
open_elections/tools/tests/test_reading.py
open_elections/validation/__init__.py
open_elections/validation/data_issues_by_state.py
open_elections/validation/integrity_report_tools.py
open_elections/validation/tests/__init__.py
open_elections/validation/tests/conftest.py
open_elections/validation/tests/test_data_corruption.py