Metadata-Version: 1.0
Name: open-elections
Version: 0.0.1
Summary: A Python package for working with Open Elections data
Home-page: UNKNOWN
Author: Open Elections
Author-email: oscar@liquidata.co
License: UNKNOWN
Platform: UNKNOWN
